LICENSE
README.md
pyproject.toml
setup.py
src/zen_matematika/__init__.py
src/zen_matematika/matematika.py
src/zen_matematika_yanwarsolah.egg-info/PKG-INFO
src/zen_matematika_yanwarsolah.egg-info/SOURCES.txt
src/zen_matematika_yanwarsolah.egg-info/dependency_links.txt
src/zen_matematika_yanwarsolah.egg-info/top_level.txt